calculator_aramas/__init__.py
calculator_aramas/calculator.py
calculator_aramas-0.1.0.dist-info/LICENSE
calculator_aramas-0.1.0.dist-info/WHEEL
calculator_aramas-0.1.0.dist-info/METADATA
calculator_aramas-0.1.0.dist-info/RECORD
