Metadata-Version: 2.1
Name: calculator_aramas
Version: 0.1.0
Summary: Calculator Aramas: A simple yet effective calculator tool.
Author-email: Aleksas Ramaska <ramaskaleksas@gmail.com>
Classifier: License :: OSI Approved :: MIT License
Project-URL: Home, http://calculator_aramas.com
